docler/__init__.py
docler/__main__.py
docler/annotators/__init__.py
docler/annotators/ai_document_annotator.py
docler/annotators/ai_image_annotator.py
docler/annotators/base.py
docler/chunkers/__init__.py
docler/chunkers/ai_chunker/__init__.py
docler/chunkers/ai_chunker/chunker.py
docler/chunkers/ai_chunker/models.py
docler/chunkers/ai_chunker/utils.py
docler/chunkers/base.py
docler/chunkers/llamaindex_chunker/__init__.py
docler/chunkers/llamaindex_chunker/chunker.py
docler/chunkers/markdown_chunker/__init__.py
docler/chunkers/markdown_chunker/chunker.py
docler/chunkers/markdown_chunker/utils.py
docler/chunkers/token_chunker/__init__.py
docler/chunkers/token_chunker/chunker.py
docler/common_types.py
docler/converters/__init__.py
docler/converters/aggregated_converter.py
docler/converters/azure_provider/__init__.py
docler/converters/azure_provider/provider.py
docler/converters/azure_provider/utils.py
docler/converters/base.py
docler/converters/datalab_provider/__init__.py
docler/converters/datalab_provider/provider.py
docler/converters/datalab_provider/utils.py
docler/converters/dir_converter.py
docler/converters/docling_provider/__init__.py
docler/converters/docling_provider/provider.py
docler/converters/docling_provider/utils.py
docler/converters/docling_remote_provider/__init__.py
docler/converters/docling_remote_provider/provider.py
docler/converters/docling_remote_provider/utils.py
docler/converters/exceptions.py
docler/converters/llamaparse_provider/__init__.py
docler/converters/llamaparse_provider/provider.py
docler/converters/llamaparse_provider/utils.py
docler/converters/llm_provider/__init__.py
docler/converters/llm_provider/provider.py
docler/converters/marker_provider/__init__.py
docler/converters/marker_provider/provider.py
docler/converters/markitdown_provider/__init__.py
docler/converters/markitdown_provider/provider.py
docler/converters/mistral_provider/__init__.py
docler/converters/mistral_provider/provider.py
docler-2.1.1.dist-info/licenses/LICENSE
docler-2.1.1.dist-info/WHEEL
docler-2.1.1.dist-info/entry_points.txt
docler-2.1.1.dist-info/METADATA
docler-2.1.1.dist-info/RECORD
