Metadata-Version: 2.4
Name: docler
Version: 2.1.1
Summary: Abstractions & Tools for OCR / document processing
Keywords: 
Author: Philipp Temminghoff
Author-email: Philipp Temminghoff <philipptemminghoff@googlemail.com>
License-Expression: MIT
License-File: LICENSE
Classifier: Development Status :: 4 - Beta
Classifier: Framework :: Pydantic
Classifier: Framework :: Pydantic :: 2
Classifier: Intended Audience :: Developers
Classifier: Operating System :: OS Independent
Classifier: Programming Language :: Python :: 3
Classifier: Programming Language :: Python :: 3 :: Only
Classifier: Programming Language :: Python :: 3.12
Classifier: Programming Language :: Python :: 3.13
Classifier: Programming Language :: Python :: 3.14
Classifier: Topic :: Documentation
Classifier: Topic :: Software Development
Classifier: Topic :: Utilities
Classifier: Typing :: Typed
Requires-Dist: anyenv>=0.4.1
Requires-Dist: mkdown>=0.12.1
Requires-Dist: pydantic
Requires-Dist: pydantic-settings>=2.8.1
Requires-Dist: pypdf
Requires-Dist: pytest-docker>=3.2.1
Requires-Dist: schemez>=0.0.1
Requires-Dist: upathtools>=0.4.3
Requires-Dist: docler[marker,azure,diffs,docling,llama-parse,marker,markitdown,mcp,mistralai,openai,server] ; extra == 'all'
Requires-Dist: agentpool[default] ; extra == 'all'
Requires-Dist: azure-ai-documentintelligence ; extra == 'azure'
Requires-Dist: diff-match-patch ; extra == 'diffs'
Requires-Dist: docling[ocrmac,vlm,rapidocr] ; python_full_version < '3.14' and extra == 'docling'
Requires-Dist: docler[mistralai,diffs,llama-parse,openai,azure] ; extra == 'light'
Requires-Dist: agentpool[default] ; extra == 'light'
Requires-Dist: llama-parse ; python_full_version < '3.14' and extra == 'llama-parse'
Requires-Dist: marker-pdf ; python_full_version < '3.14' and extra == 'marker'
Requires-Dist: markitdown[all] ; python_full_version < '3.14' and extra == 'markitdown'
Requires-Dist: fastmcp ; extra == 'mcp'
Requires-Dist: mistralai ; extra == 'mistralai'
Requires-Dist: olmocr ; python_full_version < '3.14' and extra == 'olmocr'
Requires-Dist: accelerate ; python_full_version < '3.14' and extra == 'olmocr'
Requires-Dist: openai ; extra == 'openai'
Requires-Dist: uvicorn ; extra == 'server'
Requires-Dist: fastapi ; extra == 'server'
Requires-Dist: streamlit ; python_full_version < '3.14' and extra == 'streamlit'
Requires-Dist: streambricks ; python_full_version < '3.14' and extra == 'streamlit'
Requires-Dist: tokonomics ; extra == 'token-chunking'
Requires-Python: >=3.13
Project-URL: Code coverage, https://app.codecov.io/gh/phil65/docler
Project-URL: Discussions, https://github.com/phil65/docler/discussions
Project-URL: Documentation, https://phil65.github.io/docler/
Project-URL: Issues, https://github.com/phil65/docler/issues
Project-URL: Source, https://github.com/phil65/docler
Provides-Extra: all
Provides-Extra: azure
Provides-Extra: diffs
Provides-Extra: docling
Provides-Extra: light
Provides-Extra: llama-parse
Provides-Extra: marker
Provides-Extra: markitdown
Provides-Extra: mcp
Provides-Extra: mistralai
Provides-Extra: olmocr
Provides-Extra: openai
Provides-Extra: server
Provides-Extra: streamlit
Provides-Extra: token-chunking
